transparent_classroom/__init__.py
transparent_classroom/apis.py
transparent_classroom/clients.py
transparent_classroom/entry_points.py
transparent_classroom/interfaces.py
transparent_classroom/route_components.py
transparent_classroom/routes.py
transparent_classroom/api/__init__.py
transparent_classroom/api/entry_points/__init__.py
transparent_classroom/api/enums/__init__.py
transparent_classroom/api/exceptions/__init__.py
transparent_classroom/api/interfaces/__init__.py
transparent_classroom/api/interfaces/fields/__init__.py
transparent_classroom/api/interfaces/fields/exceptions/__init__.py
transparent_classroom/api/interfaces/validators/__init__.py
transparent_classroom/api/interfaces/validators/constraints/__init__.py
transparent_classroom/api/interfaces/validators/exceptions/__init__.py
transparent_classroom/api/routing/__init__.py
transparent_classroom/api/routing/routes/__init__.py
transparent_classroom/models/__init__.py
transparent_classroom/models/utilities.py
transparent_classroom/models/deserializers/__init__.py
transparent_classroom/models/serializers/__init__.py
transparent_classroom-0.0.5.dist-info/LICENSE.md
transparent_classroom-0.0.5.dist-info/METADATA
transparent_classroom-0.0.5.dist-info/WHEEL
transparent_classroom-0.0.5.dist-info/top_level.txt
transparent_classroom-0.0.5.dist-info/RECORD
