Metadata-Version: 2.1
Name: transparent_classroom
Version: 0.0.5
Summary: Python Client for accessing Transparent Classroom's data model.
Home-page: https://github.com/dpozorski/transparent-classroom
Author: Dylan Pozorski
Author-email: dylanpozorski@gmail.com
Classifier: Programming Language :: Python :: 3
Classifier: License :: OSI Approved :: MIT License
Classifier: Operating System :: OS Independent
Requires-Python: >=3.6
License-File: LICENSE.md
Requires-Dist: setuptools
Requires-Dist: pytz
Requires-Dist: requests
